LICENSE
MANIFEST.in
README.md
setup.py
fossrit_tahrir_theme/__init__.py
fossrit_tahrir_theme.egg-info/PKG-INFO
fossrit_tahrir_theme.egg-info/SOURCES.txt
fossrit_tahrir_theme.egg-info/dependency_links.txt
fossrit_tahrir_theme.egg-info/not-zip-safe
fossrit_tahrir_theme.egg-info/top_level.txt
fossrit_tahrir_theme/static/css/monokai.css
fossrit_tahrir_theme/static/css/tahrir.css
fossrit_tahrir_theme/static/css/unsemantic-grid-mobile.css
fossrit_tahrir_theme/static/css/unsemantic-grid-responsive-tablet.css
fossrit_tahrir_theme/static/css/unsemantic-grid-responsive.css
fossrit_tahrir_theme/static/img/404.png
fossrit_tahrir_theme/static/img/404.svg
fossrit_tahrir_theme/static/img/500.png
fossrit_tahrir_theme/static/img/500.svg
fossrit_tahrir_theme/static/img/badge.png
fossrit_tahrir_theme/static/img/badge_bullet.png
fossrit_tahrir_theme/static/img/badge_bullet_fedora.png
fossrit_tahrir_theme/static/img/badger_avatar.png
fossrit_tahrir_theme/static/img/badger_avatar.svg
fossrit_tahrir_theme/static/img/favicon.ico
fossrit_tahrir_theme/static/img/fedora_logo.png
fossrit_tahrir_theme/static/img/fossrit_badges.png
fossrit_tahrir_theme/static/img/fossrit_badges.svg
fossrit_tahrir_theme/static/js/builder.js
fossrit_tahrir_theme/static/js/social.js