Metadata-Version: 1.0
Name: fossrit-tahrir-theme
Version: 0.1.6
Summary: FOSSRIT theme for the Tahrir Open Badges webapp
Home-page: https://github.com/FOSSRIT/fossrit-tahrir-theme
Author: David Gay
Author-email: oddshocks@riseup.net
License: GPLv3+
Platform: UNKNOWN
